<?xml version="1.0" encoding="UTF-8"?>
<issue>
   <issueMeta>
      <issueId>18451227</issueId>
      <issueTitle>The Broadway Journal</issueTitle>
      <issueVol>2</issueVol>
      <issueNum>25</issueNum>
      <issueDate>December 27, 1845</issueDate>
      <issueListPerson>
         <eapoe>
            <personId>eapoe</personId>
            <personName>Edgar Allan Poe</personName>
            <personIssueRole>Editor</personIssueRole>
         </eapoe>
         <eapoe>
            <personId>eapoe</personId>
            <personName>Edgar Allan Poe</personName>
            <personIssueRole>Publisher</personIssueRole>
         </eapoe>
      </issueListPerson>
   </issueMeta>
   <listBibl/>
</issue>
